autosig/__init__.py
autosig/autosig.py
autosig-0.10.0.dist-info/LICENSE
autosig-0.10.0.dist-info/WHEEL
autosig-0.10.0.dist-info/METADATA
autosig-0.10.0.dist-info/RECORD
