Metadata-Version: 2.1
Name: autosig
Version: 0.10.0
Summary: Define signatures to create beautiful APIs
Home-page: https://github.com/piccolbo/autosig
License: GPL-3.0
Author: Antonio Piccolboni
Author-email: antonio@piccolboni.info
Requires-Python: >=3.5,<4.0
Classifier: Development Status :: 4 - Beta
Classifier: Intended Audience :: Developers
Classifier: License :: OSI Approved :: GNU General Public License v3 (GPLv3)
Classifier: Programming Language :: Python :: 3
Classifier: Programming Language :: Python :: 3.5
Classifier: Programming Language :: Python :: 3.6
Classifier: Programming Language :: Python :: 3.7
Classifier: Programming Language :: Python :: 3.8
Requires-Dist: attrs (>=19.2.0)
Requires-Dist: toolz (>=0.9.0)
Project-URL: Documentation, https://autosig.readthedocs.io/en/latest/
Project-URL: Repository, https://github.com/piccolbo/autosig
